[
  {
    "source": "Test-2022C-Q1",
    "testNumber": 2022,
    "testVariant": "C",
    "questionNumber": 1,
    "type": "MCQ",
    "topic": "algebra",
    "subtopic": "exponent_rules",
    "difficulty": 1,
    "body": "$3^{-2}$ утгыг олоорой.",
    "options": {
      "A": "$\\frac{1}{9}$",
      "B": "$\\frac{1}{6}$",
      "C": "$\\frac{1}{8}$",
      "D": "$-6$",
      "E": "$1$"
    },
    "answer": "A",
    "solution": "$3^{-2}=\\frac{1}{9}$"
  },
  {
    "source": "Test-2022C-Q2",
    "testNumber": 2022,
    "testVariant": "C",
    "questionNumber": 2,
    "type": "MCQ",
    "topic": "statistics",
    "subtopic": "median",
    "difficulty": 1,
    "body": "Ангийн есөн сурагч гэрийн даалгаварт тус бүр 3, 2, 4, 6, 2, 3, 5, 2, 4 бодлого боджээ. Өгөгдлийн медианыг олоорой.",
    "options": {
      "A": "3",
      "B": "2",
      "C": "5",
      "D": "4",
      "E": "6"
    },
    "answer": "A",
    "solution": "Sorted: 2,2,2,3,3,4,4,5,6 → median=3"
  },
  {
    "source": "Test-2022C-Q3",
    "testNumber": 2022,
    "testVariant": "C",
    "questionNumber": 3,
    "type": "MCQ",
    "topic": "functions",
    "subtopic": "function_evaluation",
    "difficulty": 1,
    "body": "$f(x)=3x-1$ бол $f(3)=?$",
    "options": {
      "A": "$10$",
      "B": "$3$",
      "C": "$-1$",
      "D": "$8$",
      "E": "$9$"
    },
    "answer": "D",
    "solution": "$f(3)=3(3)-1=8$"
  },
  {
    "source": "Test-2022C-Q4",
    "testNumber": 2022,
    "testVariant": "C",
    "questionNumber": 4,
    "type": "MCQ",
    "topic": "sets",
    "subtopic": "set_union",
    "difficulty": 1,
    "body": "$A=\\{2,3,4,5,6\\}$ ба $B=\\{4,6,9\\}$ олонлогийн нэгдэл нь хэдэн элементтэй вэ?",
    "options": {
      "A": "5",
      "B": "8",
      "C": "9",
      "D": "6",
      "E": "2"
    },
    "answer": "D",
    "solution": "$A\\cup B=\\{2,3,4,5,6,9\\}$, 6 элемент"
  },
  {
    "source": "Test-2022C-Q5",
    "testNumber": 2022,
    "testVariant": "C",
    "questionNumber": 5,
    "type": "MCQ",
    "topic": "linear_algebra",
    "subtopic": "matrix_dimensions",
    "difficulty": 1,
    "body": "$A=\\begin{pmatrix}3 & 1\\end{pmatrix}$ ба $B=\\begin{pmatrix}2 & 3\\\\-3 & -8\\end{pmatrix}$ бол $A\\times B$ үржвэр матрицын хэмжээсийг олоорой.",
    "options": {
      "A": "$2\\times 1$",
      "B": "$1\\times 1$",
      "C": "$1\\times 2$",
      "D": "$2\\times 2$",
      "E": "$3\\times 1$"
    },
    "answer": "C",
    "solution": "$(1\\times2)\\times(2\\times2)=(1\\times2)$"
  },
  {
    "source": "Test-2022C-Q6",
    "testNumber": 2022,
    "testVariant": "C",
    "questionNumber": 6,
    "type": "MCQ",
    "topic": "vectors",
    "subtopic": "vector_arithmetic",
    "difficulty": 1,
    "body": "$\\vec{a}=(-5,2)$, $\\vec{b}=(3,1)$ бол $2\\vec{a}+\\vec{b}$ векторыг олоорой.",
    "options": {
      "A": "$(1,4)$",
      "B": "$(-2,3)$",
      "C": "$(-7,5)$",
      "D": "$(3,-2)$",
      "E": "$(5,-7)$"
    },
    "answer": "C",
    "solution": "$2(-5,2)+(3,1)=(-7,5)$"
  },
  {
    "source": "Test-2022C-Q7",
    "testNumber": 2022,
    "testVariant": "C",
    "questionNumber": 7,
    "type": "MCQ",
    "topic": "geometry",
    "subtopic": "translation",
    "difficulty": 1,
    "body": "$A$ гурвалжныг $\\vec{a}$ вектороор параллел зөөхөд дүр нь $B$ гурвалжин гарчээ. $\\vec{a}$ векторыг олоорой. (Графикаар өгөгдсөн)",
    "options": {
      "A": "$\\vec{a}=(2,1)$",
      "B": "$\\vec{a}=(-1,3)$",
      "C": "$\\vec{a}=(0,-2)$",
      "D": "$\\vec{a}=(-2,0)$",
      "E": "$\\vec{a}=(3,-1)$"
    },
    "answer": "E",
    "solution": "Graph-based; translation vector $(3,-1)$"
  },
  {
    "source": "Test-2022C-Q8",
    "testNumber": 2022,
    "testVariant": "C",
    "questionNumber": 8,
    "type": "MCQ",
    "topic": "calculus",
    "subtopic": "derivative_trig",
    "difficulty": 1,
    "body": "$y=\\sin 3x$ функцийн уламжлалыг олоорой.",
    "options": {
      "A": "$\\cos 3x$",
      "B": "$3\\cos 3x$",
      "C": "$-\\cos 3x$",
      "D": "$-3\\cos 3x$",
      "E": "$3\\cos x$"
    },
    "answer": "B",
    "solution": "$(\\sin 3x)'=3\\cos 3x$"
  },
  {
    "source": "Test-2022C-Q9",
    "testNumber": 2022,
    "testVariant": "C",
    "questionNumber": 9,
    "type": "MCQ",
    "topic": "arithmetic",
    "subtopic": "fraction_arithmetic",
    "difficulty": 1,
    "body": "$\\frac{7}{30}\\div\\left(1\\frac{1}{6}-\\frac{7}{8}\\right)$ утгыг олоорой.",
    "options": {
      "A": "$\\frac{6}{5}$",
      "B": "$\\frac{5}{4}$",
      "C": "$-\\frac{27}{40}$",
      "D": "$\\frac{4}{5}$",
      "E": "$\\frac{5}{6}$"
    },
    "answer": "D",
    "solution": "$1\\frac{1}{6}-\\frac{7}{8}=\\frac{7}{24}$; $\\frac{7}{30}\\div\\frac{7}{24}=\\frac{24}{30}=\\frac{4}{5}$"
  },
  {
    "source": "Test-2022C-Q10",
    "testNumber": 2022,
    "testVariant": "C",
    "questionNumber": 10,
    "type": "MCQ",
    "topic": "algebra",
    "subtopic": "ratio_algebra",
    "difficulty": 1,
    "body": "Тэгээс ялгаатай $a$, $b$ тоонуудад $\\frac{a}{3}=\\frac{b}{4}$ бол $\\frac{4a-b}{a+3b}$ утгыг олоорой.",
    "options": {
      "A": "$\\frac{4}{3}$",
      "B": "$1$",
      "C": "$\\frac{8}{13}$",
      "D": "$\\frac{13}{15}$",
      "E": "$\\frac{8}{15}$"
    },
    "answer": "E",
    "solution": "Let $a=3t$, $b=4t$: $\\frac{8t}{15t}=\\frac{8}{15}$"
  },
  {
    "source": "Test-2022C-Q11",
    "testNumber": 2022,
    "testVariant": "C",
    "questionNumber": 11,
    "type": "MCQ",
    "topic": "algebra",
    "subtopic": "radical_equations",
    "difficulty": 1,
    "body": "$(3x+9)\\cdot\\sqrt{x-2}=0$ тэгшитгэл бодоорой.",
    "options": {
      "A": "$-2,\\ 3$",
      "B": "$-3,\\ 2$",
      "C": "$2$",
      "D": "$-3$",
      "E": "$-2,\\ -3$"
    },
    "answer": "C",
    "solution": "Domain $x\\geq2$; $3x+9=0\\Rightarrow x=-3$ (invalid); $\\sqrt{x-2}=0\\Rightarrow x=2$"
  },
  {
    "source": "Test-2022C-Q12",
    "testNumber": 2022,
    "testVariant": "C",
    "questionNumber": 12,
    "type": "MCQ",
    "topic": "geometry",
    "subtopic": "median_length",
    "difficulty": 1,
    "body": "$A(-2,2)$, $B(-2,3)$, $C(6,-4)$ цэгүүдэд оройтой гурвалжны $B$ оройгоос татсан медианы уртыг олоорой.",
    "options": {
      "A": "$4\\sqrt{2}$",
      "B": "$3\\sqrt{2}$",
      "C": "$5$",
      "D": "$6$",
      "E": "$2\\sqrt{5}$"
    },
    "answer": "A",
    "solution": "Midpoint of $AC$: $M=(2,-1)$; $BM=\\sqrt{4^2+4^2}=4\\sqrt{2}$"
  },
  {
    "source": "Test-2022C-Q13",
    "testNumber": 2022,
    "testVariant": "C",
    "questionNumber": 13,
    "type": "MCQ",
    "topic": "probability",
    "subtopic": "event_probability",
    "difficulty": 1,
    "body": "60-аас хэтрэхгүй натурал тоонуудаас нэг тоо сонгон авахад 3 эсвэл 5-д хуваагдах тоо байх магадлалыг олоорой.",
    "options": {
      "A": "$\\frac{2}{15}$",
      "B": "$\\frac{8}{15}$",
      "C": "$\\frac{3}{5}$",
      "D": "$\\frac{7}{15}$",
      "E": "$\\frac{1}{4}$"
    },
    "answer": "D",
    "solution": "Div by 3: 20, div by 5: 12, div by 15: 4; total 28; $P=\\frac{28}{60}=\\frac{7}{15}$"
  },
  {
    "source": "Test-2022C-Q14",
    "testNumber": 2022,
    "testVariant": "C",
    "questionNumber": 14,
    "type": "MCQ",
    "topic": "geometry",
    "subtopic": "cylinder",
    "difficulty": 1,
    "body": "Доод суурийн талбай $36\\pi$ байх цилиндрийн тэнхлэг огтлол нь квадрат бол цилиндрийн өндрийг олоорой.",
    "options": {
      "A": "18",
      "B": "6",
      "C": "12",
      "D": "16",
      "E": "9"
    },
    "answer": "C",
    "solution": "$\\pi r^2=36\\pi\\Rightarrow r=6$; axial cross-section square $\\Rightarrow h=2r=12$"
  },
  {
    "source": "Test-2022C-Q15",
    "testNumber": 2022,
    "testVariant": "C",
    "questionNumber": 15,
    "type": "MCQ",
    "topic": "calculus",
    "subtopic": "derivative_log",
    "difficulty": 1,
    "body": "$f(x)=\\ln(x+2)$ функцийн графикийн $x=3$ цэгт татсан шүргэгч шулууны налалтыг олоорой.",
    "options": {
      "A": "$\\frac{1}{\\ln 3}$",
      "B": "$\\frac{1}{3}$",
      "C": "$\\frac{1}{\\ln 5}$",
      "D": "$\\frac{1}{2}$",
      "E": "$\\frac{1}{5}$"
    },
    "answer": "E",
    "solution": "$f'(x)=\\frac{1}{x+2}$; $f'(3)=\\frac{1}{5}$"
  },
  {
    "source": "Test-2022C-Q16",
    "testNumber": 2022,
    "testVariant": "C",
    "questionNumber": 16,
    "type": "MCQ",
    "topic": "trigonometry",
    "subtopic": "sine_rule",
    "difficulty": 1,
    "body": "$ABC$ гурвалжинд $\\angle BAC=45°$, $\\angle BCA=105°$, $AC=6$ бол $BC$ талын уртыг олоорой.",
    "options": {
      "A": "$6\\sqrt{2}$",
      "B": "$2\\sqrt{6}$",
      "C": "$3\\sqrt{2}$",
      "D": "$12$",
      "E": "$4\\sqrt{6}$"
    },
    "answer": "A",
    "solution": "$\\angle ABC=30°$; $\\frac{BC}{\\sin 45°}=\\frac{6}{\\sin 30°}\\Rightarrow BC=6\\sqrt{2}$"
  },
  {
    "source": "Test-2022C-Q17",
    "testNumber": 2022,
    "testVariant": "C",
    "questionNumber": 17,
    "type": "MCQ",
    "topic": "complex_numbers",
    "subtopic": "complex_division",
    "difficulty": 1,
    "body": "$\\frac{1+i}{2-i}$ комплекс тоог $a+bi$ хэлбэрт бичээрэй.",
    "options": {
      "A": "$\\frac{3}{5}+\\frac{3}{5}i$",
      "B": "$\\frac{1}{3}+i$",
      "C": "$\\frac{1}{5}+\\frac{3}{5}i$",
      "D": "$\\frac{2}{5}+i$",
      "E": "$\\frac{1}{2}-i$"
    },
    "answer": "C",
    "solution": "$\\frac{(1+i)(2+i)}{5}=\\frac{1+3i}{5}=\\frac{1}{5}+\\frac{3}{5}i$"
  },
  {
    "source": "Test-2022C-Q18",
    "testNumber": 2022,
    "testVariant": "C",
    "questionNumber": 18,
    "type": "MCQ",
    "topic": "statistics",
    "subtopic": "expected_value",
    "difficulty": 1,
    "body": "$X$ дискрет санамсаргүй хувьсагчийн магадлалын тархалт: $x=1$: $P=\\frac{1}{6}$, $x=2$: $P=a$, $x=3$: $P=\\frac{2}{3}$. Математик дундаж олоорой.",
    "options": {
      "A": "$\\frac{7}{2}$",
      "B": "$\\frac{11}{6}$",
      "C": "$\\frac{17}{6}$",
      "D": "$\\frac{5}{2}$",
      "E": "$\\frac{1}{6}$"
    },
    "answer": "D",
    "solution": "$a=\\frac{1}{6}$; $E(X)=\\frac{1}{6}+\\frac{2}{6}+2=\\frac{5}{2}$"
  },
  {
    "source": "Test-2022C-Q19",
    "testNumber": 2022,
    "testVariant": "C",
    "questionNumber": 19,
    "type": "MCQ",
    "topic": "vectors",
    "subtopic": "dot_product",
    "difficulty": 1,
    "body": "$\\vec{a}=(3,-2,k)$, $\\vec{b}=(k+1,4,2)$ векторуудын скаляр үржвэр $\\vec{a}\\cdot\\vec{b}=10$ бол $k$ тоог олоорой.",
    "options": {
      "A": "$\\frac{7}{5}$",
      "B": "$\\frac{17}{5}$",
      "C": "$1$",
      "D": "$\\frac{16}{5}$",
      "E": "$3$"
    },
    "answer": "E",
    "solution": "$3(k+1)-8+2k=10\\Rightarrow 5k=15\\Rightarrow k=3$"
  },
  {
    "source": "Test-2022C-Q20",
    "testNumber": 2022,
    "testVariant": "C",
    "questionNumber": 20,
    "type": "MCQ",
    "topic": "calculus",
    "subtopic": "antiderivative_polynomial",
    "difficulty": 1,
    "body": "$f'(x)=6x+1$ ба $f(0)=-2$ байх $f(x)$ функцийг олоорой.",
    "options": {
      "A": "$f(x)=3x^2+x+2$",
      "B": "$f(x)=6x^2+x-2$",
      "C": "$f(x)=3x^2+x-2$",
      "D": "$f(x)=6x^2+x+2$",
      "E": "$f(x)=6x^2-x-2$"
    },
    "answer": "C",
    "solution": "$f(x)=3x^2+x+C$; $f(0)=-2\\Rightarrow C=-2$"
  },
  {
    "source": "Test-2022C-Q21",
    "testNumber": 2022,
    "testVariant": "C",
    "questionNumber": 21,
    "type": "MCQ",
    "topic": "algebra",
    "subtopic": "algebraic_simplification",
    "difficulty": 1,
    "body": "$a=36$ ба $b=28$ бол $\\frac{a-b}{a+b}\\cdot\\sqrt{\\frac{a^2+ab}{a^2-2ab+b^2}}$ утгыг олоорой.",
    "options": {
      "A": "$\\frac{3}{4}$",
      "B": "$\\frac{7}{8}$",
      "C": "$\\frac{7}{9}$",
      "D": "$\\frac{1}{8}$",
      "E": "$\\frac{3}{32}$"
    },
    "answer": "A",
    "solution": "$=\\frac{8}{64}\\cdot\\sqrt{\\frac{36\\cdot64}{64}}=\\frac{1}{8}\\cdot6=\\frac{3}{4}$"
  },
  {
    "source": "Test-2022C-Q22",
    "testNumber": 2022,
    "testVariant": "C",
    "questionNumber": 22,
    "type": "MCQ",
    "topic": "sequences",
    "subtopic": "geometric_sequence",
    "difficulty": 1,
    "body": "Эерэг гишүүдтэй геометр прогрессийн $b_3=2$ ба $b_9=54$ бол $b_6$ гишүүнийг олоорой.",
    "options": {
      "A": "$18$",
      "B": "$2\\sqrt{3}$",
      "C": "$6$",
      "D": "$27$",
      "E": "$6\\sqrt{3}$"
    },
    "answer": "E",
    "solution": "$r^6=27\\Rightarrow r^2=3$; $b_6=2r^3=6\\sqrt{3}$"
  },
  {
    "source": "Test-2022C-Q23",
    "testNumber": 2022,
    "testVariant": "C",
    "questionNumber": 23,
    "type": "MCQ",
    "topic": "algebra",
    "subtopic": "system_log_quadratic",
    "difficulty": 1,
    "body": "$\\begin{cases}\\log_2 x=\\log_2(y+2)\\\\2y^2-x^2=17\\end{cases}$ тэгшитгэлийн системээс $(x,y)$-ийг олоорой.",
    "options": {
      "A": "$(7,9),\\;(-3,-1)$",
      "B": "$(9,7),\\;(-1,-3)$",
      "C": "$(7,9),\\;(3,1)$",
      "D": "$(9,7)$",
      "E": "$(7,9)$"
    },
    "answer": "D",
    "solution": "$x=y+2$; $y^2-4y-21=0\\Rightarrow y=7$; domain: $y=-3$ invalid; $(9,7)$"
  },
  {
    "source": "Test-2022C-Q24",
    "testNumber": 2022,
    "testVariant": "C",
    "questionNumber": 24,
    "type": "MCQ",
    "topic": "algebra",
    "subtopic": "polynomial_factoring",
    "difficulty": 1,
    "body": "$p(x)=x^2-2x+c$ олон гишүүнтийн нэг язгуур $x=-2$ бол үржигдэхүүнд задлана уу?",
    "options": {
      "A": "$(x+4)(x+2)$",
      "B": "$(x+2)(x-3)$",
      "C": "$(x-4)(x+2)$",
      "D": "$x(x-2)$",
      "E": "$(x+4)(x-2)$"
    },
    "answer": "C",
    "solution": "$p(-2)=0\\Rightarrow c=-8$; $x^2-2x-8=(x-4)(x+2)$"
  },
  {
    "source": "Test-2022C-Q25",
    "testNumber": 2022,
    "testVariant": "C",
    "questionNumber": 25,
    "type": "MCQ",
    "topic": "functions",
    "subtopic": "composite_functions",
    "difficulty": 1,
    "body": "$f(x)=x-2$ ба $g(x)=x^2+3$ функцүүдийн хувьд $g(f(x))=x+1$ байх $x$-ийг олоорой.",
    "options": {
      "A": "$0,\\ 1$",
      "B": "$2,\\ 3$",
      "C": "$1,\\ 5$",
      "D": "$0$",
      "E": "$0,\\ -1$"
    },
    "answer": "B",
    "solution": "$g(f(x))=(x-2)^2+3=x^2-4x+7=x+1\\Rightarrow x^2-5x+6=0\\Rightarrow x=2,3$"
  },
  {
    "source": "Test-2022C-Q26",
    "testNumber": 2022,
    "testVariant": "C",
    "questionNumber": 26,
    "type": "MCQ",
    "topic": "trigonometry",
    "subtopic": "trig_identity",
    "difficulty": 1,
    "body": "$\\tan\\alpha=2$ бол $\\left(\\dfrac{\\cos\\alpha}{1+\\sin\\alpha}+\\dfrac{\\cos\\alpha}{1-\\sin\\alpha}\\right)^2$ утгыг олоорой.",
    "options": {
      "A": "$16$",
      "B": "$10$",
      "C": "$12$",
      "D": "$20$",
      "E": "$18$"
    },
    "answer": "D",
    "solution": "$=\\left(\\frac{2}{\\cos\\alpha}\\right)^2=4(1+\\tan^2\\alpha)=4\\cdot5=20$"
  },
  {
    "source": "Test-2022C-Q27",
    "testNumber": 2022,
    "testVariant": "C",
    "questionNumber": 27,
    "type": "MCQ",
    "topic": "geometry",
    "subtopic": "inscribed_circle_trapezoid",
    "difficulty": 1,
    "body": "Радиус нь 4 байх тойргийг багтаасан тэгш өнцөгт трапецийн хувьд $AD-BC=6$ бол $P_{ABCD}$ периметрийг олоорой.",
    "options": {
      "A": "28",
      "B": "32",
      "C": "38",
      "D": "40",
      "E": "36"
    },
    "answer": "E",
    "solution": "$h=8$; $AB=\\sqrt{6^2+8^2}=10$; $AD+BC=AB+CD=18$; $P=36$"
  },
  {
    "source": "Test-2022C-Q28",
    "testNumber": 2022,
    "testVariant": "C",
    "questionNumber": 28,
    "type": "MCQ",
    "topic": "calculus",
    "subtopic": "definite_integral",
    "difficulty": 1,
    "body": "$\\displaystyle\\int_0^1 \\frac{e^x-1}{e^x}\\,dx$ интегралыг бодоорой.",
    "options": {
      "A": "$\\dfrac{1}{e}$",
      "B": "$\\dfrac{1}{e}+2$",
      "C": "$2-\\dfrac{1}{e}$",
      "D": "$1+\\dfrac{1}{e}$",
      "E": "$-\\dfrac{1}{e}$"
    },
    "answer": "A",
    "solution": "$\\int_0^1(1-e^{-x})dx=[x+e^{-x}]_0^1=\\frac{1}{e}$"
  },
  {
    "source": "Test-2022C-Q29",
    "testNumber": 2022,
    "testVariant": "C",
    "questionNumber": 29,
    "type": "MCQ",
    "topic": "geometry",
    "subtopic": "homothety_reflection",
    "difficulty": 1,
    "body": "$A(3;2)$ цэгийг координатын эх дээр төвтэй $k=-2$ коэффициенттэй гомотетоор хувиргахад $B$ цэг, харин $y$ тэнхлэгийн хувьд тэгш хэмтэй хувиргахад $C$ цэг үүсэв. $ABC$ гурвалжны талбайг олоорой.",
    "options": {
      "A": "$22.5$",
      "B": "$16$",
      "C": "$21$",
      "D": "$18$",
      "E": "$20.5$"
    },
    "answer": "D",
    "solution": "$B=(-6,-4)$; $C=(-3,2)$; Area$=\\frac{1}{2}|3(-6)+(-6)(0)+(-3)(6)|=18$"
  },
  {
    "source": "Test-2022C-Q30",
    "testNumber": 2022,
    "testVariant": "C",
    "questionNumber": 30,
    "type": "MCQ",
    "topic": "statistics",
    "subtopic": "combined_standard_deviation",
    "difficulty": 1,
    "body": "Сагсан бөмбөгийн нэг багийн 5 тоглогчийн $\\sum x=22$, $\\sum x^2=100$. Нөгөө багийн 5 тоглогчийн $\\sum y=25$, $\\sum y^2=171$. Эдгээр 10 тоглогчийн эхний үед авсан онооны стандарт хазайлтыг олоорой.",
    "options": {
      "A": "$\\sqrt{5.13}$",
      "B": "$\\sqrt{5.21}$",
      "C": "$\\sqrt{5.01}$",
      "D": "$\\sqrt{5.07}$",
      "E": "$\\sqrt{5.16}$"
    },
    "answer": "C",
    "solution": "$\\bar{x}=4.7$; $\\sigma^2=\\frac{271}{10}-4.7^2=5.01$; $\\sigma=\\sqrt{5.01}$"
  },
  {
    "source": "Test-2022C-Q31",
    "testNumber": 2022,
    "testVariant": "C",
    "questionNumber": 31,
    "type": "MCQ",
    "topic": "calculus",
    "subtopic": "area_between_curves",
    "difficulty": 1,
    "body": "Параболуудаар хүрээлэгдсэн дүрсийн талбайг олоорой. (Графикаар өгөгдсөн)",
    "options": {
      "A": "$20$",
      "B": "$21\\dfrac{1}{3}$",
      "C": "$20\\dfrac{2}{3}$",
      "D": "$22$",
      "E": "$22\\dfrac{1}{2}$"
    },
    "answer": "B",
    "solution": "Graph-based; area $=\\frac{64}{3}=21\\frac{1}{3}$; parabolas $y=-x^2+2x+3$ and $y=x^2-2x-3$, $x\\in[-1,3]$"
  },
  {
    "source": "Test-2022C-Q32",
    "testNumber": 2022,
    "testVariant": "C",
    "questionNumber": 32,
    "type": "MCQ",
    "topic": "algebra",
    "subtopic": "quadratic_inequality",
    "difficulty": 1,
    "body": "$a>0$ тоо байг. $x^2-(a-2)x-2a<0$ тэнцэтгэл биш яг гурван бүхэл шийдтэй байх $a$ тооны утгын мужийг олоорой.",
    "options": {
      "A": "$0<a<1$",
      "B": "$1<a<2$",
      "C": "$0<a\\leq 1$",
      "D": "$1<a\\leq 2$",
      "E": "$0<a<2$"
    },
    "answer": "D",
    "solution": "$(x-a)(x+2)<0\\Rightarrow -2<x<a$; integers $\\{-1,0,1\\}\\Rightarrow 1<a\\leq2$"
  },
  {
    "source": "Test-2022C-Q33",
    "testNumber": 2022,
    "testVariant": "C",
    "questionNumber": 33,
    "type": "MCQ",
    "topic": "geometry",
    "subtopic": "circle_tangent_line",
    "difficulty": 1,
    "body": "Координатын эхэд төвтэй бөгөөд $2x+\\sqrt{5}y-2\\sqrt{5}=0$ шулууныг шүргэх тойргийн тэгшитгэл бичээрэй.",
    "options": {
      "A": "$x^2+y^2=\\dfrac{49}{25}$",
      "B": "$x^2+y^2=\\dfrac{16}{7}$",
      "C": "$x^2+y^2=\\dfrac{20}{9}$",
      "D": "$x^2+y^2=\\dfrac{12}{5}$",
      "E": "$x^2+y^2=\\dfrac{25}{16}$"
    },
    "answer": "C",
    "solution": "$r=\\frac{2\\sqrt{5}}{\\sqrt{4+5}}=\\frac{2\\sqrt{5}}{3}$; $r^2=\\frac{20}{9}$"
  },
  {
    "source": "Test-2022C-Q34",
    "testNumber": 2022,
    "testVariant": "C",
    "questionNumber": 34,
    "type": "MCQ",
    "topic": "probability",
    "subtopic": "variance",
    "difficulty": 1,
    "body": "Уутанд 3 улаан, 2 цагаан бөмбөг байв. Уутнаас санамсаргүйгээр хоёр бөмбөг сонгон авахад гарч ирсэн цагаан бөмбөгний тоог $X$ гэе. $X$-ийн дисперсийг олоорой.",
    "options": {
      "A": "$\\dfrac{2}{5}$",
      "B": "$\\dfrac{1}{5}$",
      "C": "$\\dfrac{49}{100}$",
      "D": "$\\dfrac{9}{25}$",
      "E": "$\\dfrac{4}{25}$"
    },
    "answer": "D",
    "solution": "$E(X)=\\frac{4}{5}$; $E(X^2)=1$; $D(X)=\\frac{9}{25}$"
  },
  {
    "source": "Test-2022C-Q35",
    "testNumber": 2022,
    "testVariant": "C",
    "questionNumber": 35,
    "type": "MCQ",
    "topic": "vectors",
    "subtopic": "parallelogram_vectors",
    "difficulty": 1,
    "body": "$OABC$ параллелограммын $BC$ талыг $BE:EC=2:3$ харьцаагаар хуваах цэгийг $E$ гэе. $AC$ диагональ $OE$ хэрчимтэй $M$ цэгт огтлолцдог байв. $\\overrightarrow{OA}=\\vec{a}$ ба $\\overrightarrow{OC}=\\vec{c}$ вектороор $\\overrightarrow{OM}$ векторыг илэрхийлээрэй.",
    "options": {
      "A": "$\\dfrac{3\\vec{a}}{5}+\\dfrac{2\\vec{c}}{5}$",
      "B": "$\\dfrac{9\\vec{a}}{25}+\\dfrac{3\\vec{c}}{5}$",
      "C": "$\\dfrac{3\\vec{a}}{8}+\\dfrac{5\\vec{c}}{8}$",
      "D": "$\\dfrac{6\\vec{a}}{25}+\\dfrac{3\\vec{c}}{5}$",
      "E": "$\\dfrac{\\vec{a}}{4}+\\dfrac{5\\vec{c}}{8}$"
    },
    "answer": "C",
    "solution": "$E=\\frac{3}{5}\\vec{a}+\\vec{c}$; $M$ on $OE$ at $t=\\frac{5}{8}$; $\\overrightarrow{OM}=\\frac{3\\vec{a}}{8}+\\frac{5\\vec{c}}{8}$"
  },
  {
    "source": "Test-2022C-Q36",
    "testNumber": 2022,
    "testVariant": "C",
    "questionNumber": 36,
    "type": "MCQ",
    "topic": "algebra",
    "subtopic": "polynomial_remainder",
    "difficulty": 1,
    "body": "$P(x)$ олон гишүүнтийг $x-1$-д хуваахад 2 үлдэх ба $x^2+x+1$-д хуваахад $2x-3$ үлдэнэ. $P(x)$ олон гишүүнтийг $(x-1)(x^2+x+1)$ олон гишүүнтэд хуваахад гарах үлдэгдлийг олоорой.",
    "options": {
      "A": "$x^2-x+2$",
      "B": "$4x-6$",
      "C": "$x^2+2x-3$",
      "D": "$x^2+3x-2$",
      "E": "$-x^2+x+2$"
    },
    "answer": "D",
    "solution": "Remainder $ax^2+bx+c$; $a+b+c=2$, $b-a=2$, $c-a=-3\\Rightarrow a=1,b=3,c=-2$"
  }
]